schema_salad/__init__.py
schema_salad/__main__.py
schema_salad/_version.py
schema_salad/codegen.py
schema_salad/codegen_base.py
schema_salad/cpp_codegen.py
schema_salad/dlang_codegen.py
schema_salad/dotnet_codegen.py
schema_salad/exceptions.py
schema_salad/fetcher.py
schema_salad/java_codegen.py
schema_salad/jsonld_context.py
schema_salad/main.py
schema_salad/makedoc.py
schema_salad/metaschema.py
schema_salad/py.typed
schema_salad/python_codegen.py
schema_salad/python_codegen_support.py
schema_salad/ref_resolver.py
schema_salad/schema.py
schema_salad/sourceline.py
schema_salad/typescript_codegen.py
schema_salad/utils.py
schema_salad/validate.py
schema_salad/avro/__init__.py
schema_salad/avro/schema.py
schema_salad/dotnet/AssemblyInfo.cs
schema_salad/dotnet/LICENSE
schema_salad/dotnet/Project.csproj.template
schema_salad/dotnet/README.md
schema_salad/dotnet/Solution.sln
schema_salad/dotnet/Test.csproj.template
schema_salad/dotnet/docfx.json
schema_salad/dotnet/editorconfig
schema_salad/dotnet/gitignore
schema_salad/dotnet/DocFx/filterConfig.yml
schema_salad/dotnet/DocFx/index.md
schema_salad/dotnet/DocFx/toc.yml
schema_salad/dotnet/Test/runsettings.xml
schema_salad/dotnet/Test/data/test.txt
schema_salad/dotnet/Test/src/ExampleTests.cs
schema_salad/dotnet/Test/src/FetcherTests.cs
schema_salad/dotnet/Test/src/UtilitiesTests.cs
schema_salad/dotnet/util/Fetcher.cs
schema_salad/dotnet/util/LoaderInstances.cs
schema_salad/dotnet/util/LoadingOptions.cs
schema_salad/dotnet/util/Saveable.cs
schema_salad/dotnet/util/ScalarNodeTypeResolver.cs
schema_salad/dotnet/util/UriExtensions.cs
schema_salad/dotnet/util/Utilities.cs
schema_salad/dotnet/util/ValidationException.cs
schema_salad/dotnet/util/Vocabs.cs
schema_salad/dotnet/util/Loaders/AnyLoader.cs
schema_salad/dotnet/util/Loaders/ArrayLoader.cs
schema_salad/dotnet/util/Loaders/EnumLoader.cs
schema_salad/dotnet/util/Loaders/ExpressionLoader.cs
schema_salad/dotnet/util/Loaders/IdMapLoader.cs
schema_salad-8.9.20250408123006.dist-info/licenses/LICENSE.txt
schema_salad-8.9.20250408123006.dist-info/METADATA
schema_salad-8.9.20250408123006.dist-info/WHEEL
schema_salad-8.9.20250408123006.dist-info/entry_points.txt
schema_salad-8.9.20250408123006.dist-info/top_level.txt
schema_salad-8.9.20250408123006.dist-info/zip-safe
schema_salad-8.9.20250408123006.dist-info/RECORD
