Metadata-Version: 2.4
Name: schema-salad
Version: 8.9.20250408123006
Summary: Schema Annotations for Linked Avro Data (SALAD)
Home-page: https://schema-salad.readthedocs.io/
Download-URL: https://github.com/common-workflow-language/schema_salad/releases
Author: Common workflow language working group
Author-email: common-workflow-language@googlegroups.com
License: Apache 2.0
Classifier: Environment :: Console
Classifier: Intended Audience :: Science/Research
Classifier: License :: OSI Approved :: Apache Software License
Classifier: Operating System :: POSIX
Classifier: Operating System :: MacOS :: MacOS X
Classifier: Development Status :: 5 - Production/Stable
Classifier: Programming Language :: Python :: 3.9
Classifier: Programming Language :: Python :: 3.10
Classifier: Programming Language :: Python :: 3.11
Classifier: Programming Language :: Python :: 3.12
Classifier: Programming Language :: Python :: 3.13
Classifier: Typing :: Typed
Requires-Python: >=3.9,<3.14
License-File: LICENSE.txt
Requires-Dist: requests>=1.0
Requires-Dist: ruamel.yaml<0.19,>=0.17.6
Requires-Dist: rdflib<8.0.0,>=4.2.2
Requires-Dist: mistune<3.1,>=3
Requires-Dist: CacheControl[filecache]<0.15,>=0.13.1
Requires-Dist: mypy_extensions
Provides-Extra: docs
Requires-Dist: sphinx>=2.2; extra == "docs"
Requires-Dist: sphinx-rtd-theme>=1; extra == "docs"
Requires-Dist: pytest<9; extra == "docs"
Requires-Dist: sphinx-autoapi; extra == "docs"
Requires-Dist: sphinx-autodoc-typehints; extra == "docs"
Requires-Dist: sphinxcontrib-autoprogram; extra == "docs"
Provides-Extra: pycodegen
Requires-Dist: black; extra == "pycodegen"
Dynamic: author
Dynamic: author-email
Dynamic: classifier
Dynamic: description
Dynamic: description-content-type
Dynamic: download-url
Dynamic: home-page
Dynamic: license
Dynamic: license-file
Dynamic: provides-extra
Dynamic: requires-dist
Dynamic: requires-python
Dynamic: summary
